tno/mpc/protocols/risk_propagation/__init__.py
tno/mpc/protocols/risk_propagation/account.py
tno/mpc/protocols/risk_propagation/accounts.py
tno/mpc/protocols/risk_propagation/bank.py
tno/mpc/protocols/risk_propagation/exceptions.py
tno/mpc/protocols/risk_propagation/player.py
tno/mpc/protocols/risk_propagation/py.typed
tno/mpc/protocols/risk_propagation/transaction.py
tno/mpc/protocols/risk_propagation/transactions.py
tno/mpc/protocols/risk_propagation/test/__init__.py
tno/mpc/protocols/risk_propagation/test/conftest.py
tno/mpc/protocols/risk_propagation/test/plaintext_risk_propagation.py
tno/mpc/protocols/risk_propagation/test/test_comparison_against_plaintext.py
tno/mpc/protocols/risk_propagation/test/test_generate_keys.py
tno/mpc/protocols/risk_propagation/test/test_risk_propagation.py
tno/mpc/protocols/risk_propagation/test/test_store_load_results.py
tno/mpc/protocols/risk_propagation/test/test_data/__init__.py
tno/mpc/protocols/risk_propagation/test/test_data/generate_test_case_data.py
tno/mpc/protocols/risk_propagation/test/test_data/keys/distributed_key_threshold_1_3parties_0.obj
tno/mpc/protocols/risk_propagation/test/test_data/keys/distributed_key_threshold_1_3parties_1.obj
tno/mpc/protocols/risk_propagation/test/test_data/keys/distributed_key_threshold_1_3parties_2.obj
tno/mpc/protocols/risk_propagation/test/test_data/missing_nodes/__init__.py
tno/mpc/protocols/risk_propagation/test/test_data/missing_nodes/nodes_all.csv
tno/mpc/protocols/risk_propagation/test/test_data/missing_nodes/nodes_local0.csv
tno/mpc/protocols/risk_propagation/test/test_data/missing_nodes/nodes_local1.csv
tno/mpc/protocols/risk_propagation/test/test_data/missing_nodes/nodes_local2.csv
tno/mpc/protocols/risk_propagation/test/test_data/missing_nodes/transactions_all_period0.csv
tno/mpc/protocols/risk_propagation/test/test_data/missing_nodes/transactions_all_period1.csv
tno/mpc/protocols/risk_propagation/test/test_data/missing_nodes/transactions_all_period2.csv
tno_mpc_protocols_risk_propagation-2.3.4.dist-info/licenses/LICENSE
tno_mpc_protocols_risk_propagation-2.3.4.dist-info/METADATA
tno_mpc_protocols_risk_propagation-2.3.4.dist-info/WHEEL
tno_mpc_protocols_risk_propagation-2.3.4.dist-info/top_level.txt
tno_mpc_protocols_risk_propagation-2.3.4.dist-info/RECORD
