Metadata-Version: 2.4
Name: tno.mpc.protocols.risk_propagation
Version: 2.3.4
Summary: Secure risk propagation using distributed Paillier
Author-email: TNO PET Lab <petlab@tno.nl>
Maintainer-email: TNO PET Lab <petlab@tno.nl>
License: Apache License, Version 2.0
Project-URL: Homepage, https://pet.tno.nl/
Project-URL: Documentation, https://docs.pet.tno.nl/mpc/protocols/risk_propagation/2.3.4
Project-URL: Source, https://github.com/TNO-MPC/protocols.risk_propagation
Keywords: TNO,MPC,multi-party computation,protocols,risk propagation
Platform: any
Classifier: License :: OSI Approved :: Apache Software License
Classifier: Programming Language :: Python :: 3
Classifier: Operating System :: OS Independent
Classifier: Intended Audience :: Developers
Classifier: Intended Audience :: Information Technology
Classifier: Intended Audience :: Science/Research
Classifier: Typing :: Typed
Classifier: Topic :: Security :: Cryptography
Requires-Python: >=3.9
License-File: LICENSE
Requires-Dist: numpy<3,>=1.24
Requires-Dist: tno.mpc.communication>=4.8.1,~=4.8
Requires-Dist: tno.mpc.encryption_schemes.paillier
Requires-Dist: tno.mpc.protocols.distributed_keygen~=4.0
Provides-Extra: gmpy
Requires-Dist: tno.mpc.encryption_schemes.paillier[gmpy]; extra == "gmpy"
Requires-Dist: tno.mpc.protocols.distributed_keygen[gmpy]; extra == "gmpy"
Provides-Extra: tests
Requires-Dist: numpy>=1.21; extra == "tests"
Requires-Dist: pandas; extra == "tests"
Requires-Dist: pandas-stubs; extra == "tests"
Requires-Dist: pytest>=8.1; extra == "tests"
Requires-Dist: pytest-asyncio; extra == "tests"
Dynamic: license-file
